README.md
setup.py
remote_graphcast/__init__.py
remote_graphcast.egg-info/PKG-INFO
remote_graphcast.egg-info/SOURCES.txt
remote_graphcast.egg-info/dependency_links.txt
remote_graphcast.egg-info/requires.txt
remote_graphcast.egg-info/top_level.txt
remote_graphcast/gcutils/__init__.py
remote_graphcast/gcutils/cdsutils.py
remote_graphcast/gcutils/constants.py
remote_graphcast/gcutils/inpututils.py
remote_graphcast/gcutils/log_config.py
remote_graphcast/gcutils/test_cdsutils.py
remote_graphcast/sdk/__init__.py
remote_graphcast/sdk/cli.py
remote_graphcast/sdk/remote_cast.py