Metadata-Version: 2.1
Name: remote-graphcast
Version: 0.0.9
Summary: Allows people without massive GPUs to easily run graphcast on remote runpod servers
Home-page: https://github.com/Lewington-pitsos/remote-graphcast
Author: Louka Ewington-Pitsos
Author-email: lewingtonpitsos@gmail.com
License: UNKNOWN
Platform: UNKNOWN
Classifier: Programming Language :: Python :: 3
Classifier: License :: OSI Approved :: MIT License
Classifier: Operating System :: OS Independent
Requires-Python: >=3.8
